masakaridashboard/__init__.py
masakaridashboard/dashboard.py
masakaridashboard/handle_errors.py
masakaridashboard/version.py
masakaridashboard/api/__init__.py
masakaridashboard/api/api.py
masakaridashboard/conf/masakari_policy.yaml
masakaridashboard/default/__init__.py
masakaridashboard/default/panel.py
masakaridashboard/default/templates/default/base.html
masakaridashboard/default/templates/default/table.html
masakaridashboard/hosts/__init__.py
masakaridashboard/hosts/forms.py
masakaridashboard/hosts/panel.py
masakaridashboard/hosts/tables.py
masakaridashboard/hosts/tabs.py
masakaridashboard/hosts/tests.py
masakaridashboard/hosts/urls.py
masakaridashboard/hosts/views.py
masakaridashboard/hosts/templates/hosts/_detail_overview.html
masakaridashboard/hosts/templates/hosts/_update.html
masakaridashboard/hosts/templates/hosts/detail.html
masakaridashboard/hosts/templates/hosts/index.html
masakaridashboard/hosts/templates/hosts/update.html
masakaridashboard/local/__init__.py
masakaridashboard/local/enabled/_50_masakaridashboard.py
masakaridashboard/local/enabled/__init__.py
masakaridashboard/local/local_settings.d/_50_masakari.py
masakaridashboard/notifications/__init__.py
masakaridashboard/notifications/panel.py
masakaridashboard/notifications/tables.py
masakaridashboard/notifications/tabs.py
masakaridashboard/notifications/tests.py
masakaridashboard/notifications/urls.py
masakaridashboard/notifications/views.py
masakaridashboard/notifications/templates/notifications/_detail_overview.html
masakaridashboard/notifications/templates/notifications/_progress_detail.html
masakaridashboard/notifications/templates/notifications/index.html
masakaridashboard/segments/__init__.py
masakaridashboard/segments/forms.py
masakaridashboard/segments/panel.py
masakaridashboard/segments/tables.py
masakaridashboard/segments/tabs.py
masakaridashboard/segments/tests.py
masakaridashboard/segments/urls.py
masakaridashboard/segments/views.py
masakari_dashboard-13.0.0.dist-info/AUTHORS
masakari_dashboard-13.0.0.dist-info/LICENSE
masakari_dashboard-13.0.0.dist-info/METADATA
masakari_dashboard-13.0.0.dist-info/WHEEL
masakari_dashboard-13.0.0.dist-info/pbr.json
masakari_dashboard-13.0.0.dist-info/top_level.txt
masakari_dashboard-13.0.0.dist-info/RECORD
